<source_model_fault magnitude_type="Mw">
  <fault 
  name = "Newie Fault"
  event_type = "crustal fault">
  
    <geometry 
        dip= "45" 
        out_of_dip_theta = "0"
        delta_theta = "0" 
        depth_top_seismogenic = "2"
        depth_bottom_seismogenic = "10"
        slab_width = "0">
        <trace> 	
            <start lat="-33.0" lon="151.5" />
            <end lat="-33.0" lon="151.8" />
        </trace>
    </geometry>
      
    <recurrence_model
       distribution = "bounded_gutenberg_richter"
       recurrence_min_mag = "3.5" 
       recurrence_max_mag = "6.5" 
       slip_rate = "10.0" 
       b = "1">
      <event_generation 
        generation_min_mag = "3.5"
        number_of_mag_sample_bins = "15" 
        number_of_events = "1500" />
    </recurrence_model>
           
  </fault>
</source_model_fault>
